LICENSE.md
MANIFEST.in
README.md
pyproject.toml
setup.py
src/_core/ExtraFormulas/mathaddon.cpp
src/_core/ExtraFormulas/mathaddon.h
src/_core/_Activity/Activity.cpp
src/_core/_Activity/Activity.h
src/_core/_Activity/Activity_API.h
src/_core/_Activity/pysplineaddon.h
src/_core/_Models/Models.cpp
src/_core/_Models/Models.h
src/_core/_Models/Models_C_API.h
src/_core/_Models/Models_M_API.h
src/_core/_Models/model_structure.h
src/_core/_Simulation/_Simulation.cpp
src/_core/_Simulation/_Simulation.h
src/_core/_StringList/_StringList.cpp
src/_core/_StringList/_StringList.h
src/_core/_StringList/_StringList_CPP_API.h
src/_core/_StringList/_StringList_C_API.h
src/_core/_StringList/_StringList_C_API_defines.h
src/_core/_debug/debug.cpp
src/_core/_debug/debug.h
src/_core/include/pyarraymacros.h
src/_core/include/timescales.h
src/_core/include/sundials/sundials_config.h
src/_core/include/sundials/sundials_export.h
src/_core/sund_sundials/sund_cvode.cpp
src/_core/sund_sundials/sund_ida.cpp
src/_core/sund_sundials/sund_sundials_flags.h
src/_core/sund_sundials/sund_sundials_interface.h
src/sund/__init__.py
src/sund/model_validation.py
src/sund/tools.py
src/sund/uninstall_helper.py
src/sund/utils.py
src/sund.egg-info/PKG-INFO
src/sund.egg-info/SOURCES.txt
src/sund.egg-info/dependency_links.txt
src/sund.egg-info/entry_points.txt
src/sund.egg-info/requires.txt
src/sund.egg-info/top_level.txt
src/sund/_model_deps/_include/Models_M_API.h
src/sund/_model_deps/_include/mathaddon.h
src/sund/_model_deps/_include/model_structure.h
src/sund/_model_deps/_include/pyarraymacros.h
src/sund/_model_deps/_include/sund_sundials_flags.h
src/sund/_model_deps/_include/timescales.h
src/sund/_model_deps/_src/mathaddon.cpp
src/third_party/sundials/include/cvode/cvode.h
src/third_party/sundials/include/cvode/cvode_bandpre.h
src/third_party/sundials/include/cvode/cvode_bbdpre.h
src/third_party/sundials/include/cvode/cvode_diag.h
src/third_party/sundials/include/cvode/cvode_ls.h
src/third_party/sundials/include/cvode/cvode_proj.h
src/third_party/sundials/include/ida/ida.h
src/third_party/sundials/include/ida/ida_bbdpre.h
src/third_party/sundials/include/ida/ida_ls.h
