Metadata-Version: 2.4
Name: sund
Version: 2.0.4
Summary: A simulation toolbox for ODE and DAE systems, with focus on systems biology applications.
Author: ISB group @ Linköping University
Maintainer-email: William Lövfors <william.lovfors@liu.se>, Henrik Podéus <henrik.podeus.derelov@liu.se>
License-Expression: MIT
Project-URL: Homepage, https://isbgroup.eu/sund-toolbox
Project-URL: Repository, https://gitlab.liu.se/ISBgroup/projects/sund
Keywords: sund,simulation,ODE,DAE,modeling,toolbox,systems biology
Classifier: Programming Language :: Python
Classifier: Programming Language :: Python :: 3
Classifier: Programming Language :: Python :: 3 :: Only
Classifier: Programming Language :: Python :: 3.10
Classifier: Programming Language :: Python :: 3.11
Classifier: Programming Language :: Python :: 3.12
Classifier: Programming Language :: Python :: 3.13
Classifier: Programming Language :: Python :: 3.14
Classifier: Intended Audience :: Science/Research
Classifier: Topic :: Scientific/Engineering
Requires-Python: >=3.10
License-File: LICENSE.md
Requires-Dist: numpy>=2.0
Requires-Dist: setuptools>=80.0
Dynamic: license-file
